{
  "Name": "AND",
  "NameLocation": 0,
  "ChipType": 0,
  "Size": {
    "x": 0.575,
    "y": 0.5
  },
  "Colour": {
    "r": 0.129502609,
    "g": 0.7716955,
    "b": 0.212776944,
    "a": 1
  },
  "InputPins":[
    {
      "Name":"IN",
      "ID":457018231,
      "Position":{
        "x":-9.86051,
        "y":2.2906
      },
      "BitCount":1,
      "Colour":0,
      "ValueDisplayMode":0
    },
    {
      "Name":"IN",
      "ID":1407958138,
      "Position":{
        "x":-9.92385,
        "y":0.21748
      },
      "BitCount":1,
      "Colour":0,
      "ValueDisplayMode":0
    }
  ],
  "OutputPins":[
    {
      "Name":"OUT",
      "ID":1287000259,
      "Position":{
        "x":-4.2761,
        "y":1.28342
      },
      "BitCount":1,
      "Colour":0,
      "ValueDisplayMode":0
    }
  ],
  "SubChips":[
    {
      "Name":"NAND",
      "ID":1797615807,
      "Label":"",
      "Position":{
        "x":-7.74538,
        "y":1.26342
      },
      "OutputPinColourInfo":[{"PinColour":0,"PinID":2}],
      "InternalData":null
    },
    {
      "Name":"NAND",
      "ID":1885017790,
      "Label":"",
      "Position":{
        "x":-6.40717,
        "y":1.28677
      },
      "OutputPinColourInfo":[{"PinColour":0,"PinID":2}],
      "InternalData":null
    }
  ],
  "Wires":[
    {
      "SourcePinAddress":{
        "PinID":0,
        "PinOwnerID":457018231
      },
      "TargetPinAddress":{
        "PinID":0,
        "PinOwnerID":1797615807
      },
      "ConnectionType":0,
      "ConnectedWireIndex":-1,
      "ConnectedWireSegmentIndex":-1,
      "Points":[{"x":0.0,"y":0.0},{"x":0.0,"y":0.0}]
    },
    {
      "SourcePinAddress":{
        "PinID":0,
        "PinOwnerID":1407958138
      },
      "TargetPinAddress":{
        "PinID":1,
        "PinOwnerID":1797615807
      },
      "ConnectionType":0,
      "ConnectedWireIndex":-1,
      "ConnectedWireSegmentIndex":-1,
      "Points":[{"x":0.0,"y":0.0},{"x":0.0,"y":0.0}]
    },
    {
      "SourcePinAddress":{
        "PinID":2,
        "PinOwnerID":1885017790
      },
      "TargetPinAddress":{
        "PinID":0,
        "PinOwnerID":1287000259
      },
      "ConnectionType":0,
      "ConnectedWireIndex":-1,
      "ConnectedWireSegmentIndex":-1,
      "Points":[{"x":0.0,"y":0.0},{"x":0.0,"y":0.0}]
    },
    {
      "SourcePinAddress":{
        "PinID":2,
        "PinOwnerID":1797615807
      },
      "TargetPinAddress":{
        "PinID":0,
        "PinOwnerID":1885017790
      },
      "ConnectionType":0,
      "ConnectedWireIndex":-1,
      "ConnectedWireSegmentIndex":-1,
      "Points":[{"x":0.0,"y":0.0},{"x":0.0,"y":0.0}]
    },
    {
      "SourcePinAddress":{
        "PinID":2,
        "PinOwnerID":1797615807
      },
      "TargetPinAddress":{
        "PinID":1,
        "PinOwnerID":1885017790
      },
      "ConnectionType":0,
      "ConnectedWireIndex":-1,
      "ConnectedWireSegmentIndex":-1,
      "Points":[{"x":0.0,"y":0.0},{"x":0.0,"y":0.0}]
    }
  ],
  "Displays":[]
}