{
  "DLSVersion": "2.1.5",
  "Name": "Compare 8B",
  "NameLocation": 0,
  "ChipType": 0,
  "Size": {
    "x": 1.25,
    "y": 1.0
  },
  "Colour": {
    "r": 0.3057904,
    "g": 0.8335621,
    "b": 0.185179025,
    "a": 1
  },
  "InputPins":[
    {
      "Name":"A",
      "ID":648137279,
      "Position":{
        "x":-3.55505,
        "y":1.0086
      },
      "BitCount":8,
      "Colour":0,
      "ValueDisplayMode":1
    },
    {
      "Name":"B",
      "ID":2080953887,
      "Position":{
        "x":-3.55505,
        "y":-0.99057
      },
      "BitCount":8,
      "Colour":0,
      "ValueDisplayMode":1
    }
  ],
  "OutputPins":[
    {
      "Name":"A < B",
      "ID":39465496,
      "Position":{
        "x":22.16866,
        "y":0.98382
      },
      "BitCount":1,
      "Colour":0,
      "ValueDisplayMode":0
    },
    {
      "Name":"A > B",
      "ID":1745145026,
      "Position":{
        "x":22.16866,
        "y":-1.07337
      },
      "BitCount":1,
      "Colour":0,
      "ValueDisplayMode":0
    },
    {
      "Name":"A = B",
      "ID":1280870580,
      "Position":{
        "x":22.18277,
        "y":-3.12919
      },
      "BitCount":1,
      "Colour":0,
      "ValueDisplayMode":0
    }
  ],
  "SubChips":[
    {
      "Name":"Compare 4B",
      "ID":20941381,
      "Label":"",
      "Position":{
        "x":3.18276,
        "y":0.65414
      },
      "OutputPinColourInfo":[{"PinColour":0,"PinID":39465496},{"PinColour":0,"PinID":1745145026},{"PinColour":0,"PinID":1280870580}],
      "InternalData":null
    },
    {
      "Name":"8-4BIT",
      "ID":1188044618,
      "Label":"",
      "Position":{
        "x":-1.30867,
        "y":0.97635
      },
      "OutputPinColourInfo":[{"PinColour":0,"PinID":1},{"PinColour":0,"PinID":2}],
      "InternalData":null
    },
    {
      "Name":"8-4BIT",
      "ID":1395849307,
      "Label":"",
      "Position":{
        "x":-1.28718,
        "y":-1.02281
      },
      "OutputPinColourInfo":[{"PinColour":0,"PinID":1},{"PinColour":0,"PinID":2}],
      "InternalData":null
    },
    {
      "Name":"Compare 4B",
      "ID":1013134490,
      "Label":"",
      "Position":{
        "x":3.18981,
        "y":-0.30205
      },
      "OutputPinColourInfo":[{"PinColour":0,"PinID":39465496},{"PinColour":0,"PinID":1745145026},{"PinColour":0,"PinID":1280870580}],
      "InternalData":null
    },
    {
      "Name":"AND",
      "ID":874559719,
      "Label":"",
      "Position":{
        "x":7.17298,
        "y":-3.15122
      },
      "OutputPinColourInfo":[{"PinColour":0,"PinID":1287000259}],
      "InternalData":null
    },
    {
      "Name":"AND",
      "ID":577456713,
      "Label":"",
      "Position":{
        "x":7.17298,
        "y":1.12544
      },
      "OutputPinColourInfo":[{"PinColour":0,"PinID":1287000259}],
      "InternalData":null
    },
    {
      "Name":"AND",
      "ID":2041417898,
      "Label":"",
      "Position":{
        "x":7.17298,
        "y":0.14098
      },
      "OutputPinColourInfo":[{"PinColour":0,"PinID":1287000259}],
      "InternalData":null
    },
    {
      "Name":"OR",
      "ID":31910896,
      "Label":"",
      "Position":{
        "x":15.14978,
        "y":-0.74527
      },
      "OutputPinColourInfo":[{"PinColour":0,"PinID":1935310050}],
      "InternalData":null
    },
    {
      "Name":"OR",
      "ID":1456596328,
      "Label":"",
      "Position":{
        "x":15.55504,
        "y":1.31718
      },
      "OutputPinColourInfo":[{"PinColour":0,"PinID":1935310050}],
      "InternalData":null
    }
  ],
  "Wires":[
    {
      "SourcePinAddress":{
        "PinID":0,
        "PinOwnerID":648137279
      },
      "TargetPinAddress":{
        "PinID":0,
        "PinOwnerID":1188044618
      },
      "ConnectionType":0,
      "ConnectedWireIndex":-1,
      "ConnectedWireSegmentIndex":-1,
      "Points":[{"x":0.0,"y":0.0},{"x":0.0,"y":0.0}]
    },
    {
      "SourcePinAddress":{
        "PinID":0,
        "PinOwnerID":2080953887
      },
      "TargetPinAddress":{
        "PinID":0,
        "PinOwnerID":1395849307
      },
      "ConnectionType":0,
      "ConnectedWireIndex":-1,
      "ConnectedWireSegmentIndex":-1,
      "Points":[{"x":0.0,"y":0.0},{"x":0.0,"y":0.0}]
    },
    {
      "SourcePinAddress":{
        "PinID":2,
        "PinOwnerID":1395849307
      },
      "TargetPinAddress":{
        "PinID":1486540576,
        "PinOwnerID":1013134490
      },
      "ConnectionType":0,
      "ConnectedWireIndex":-1,
      "ConnectedWireSegmentIndex":-1,
      "Points":[{"x":0.0,"y":0.0},{"x":0.0,"y":0.0}]
    },
    {
      "SourcePinAddress":{
        "PinID":2,
        "PinOwnerID":1188044618
      },
      "TargetPinAddress":{
        "PinID":1849308770,
        "PinOwnerID":1013134490
      },
      "ConnectionType":0,
      "ConnectedWireIndex":-1,
      "ConnectedWireSegmentIndex":-1,
      "Points":[{"x":0.0,"y":0.0},{"x":0.0,"y":0.0}]
    },
    {
      "SourcePinAddress":{
        "PinID":1,
        "PinOwnerID":1395849307
      },
      "TargetPinAddress":{
        "PinID":1486540576,
        "PinOwnerID":20941381
      },
      "ConnectionType":0,
      "ConnectedWireIndex":-1,
      "ConnectedWireSegmentIndex":-1,
      "Points":[{"x":0.0,"y":0.0},{"x":0.0,"y":0.0}]
    },
    {
      "SourcePinAddress":{
        "PinID":1,
        "PinOwnerID":1188044618
      },
      "TargetPinAddress":{
        "PinID":1849308770,
        "PinOwnerID":20941381
      },
      "ConnectionType":0,
      "ConnectedWireIndex":-1,
      "ConnectedWireSegmentIndex":-1,
      "Points":[{"x":0.0,"y":0.0},{"x":0.0,"y":0.0}]
    },
    {
      "SourcePinAddress":{
        "PinID":1280870580,
        "PinOwnerID":20941381
      },
      "TargetPinAddress":{
        "PinID":457018231,
        "PinOwnerID":874559719
      },
      "ConnectionType":0,
      "ConnectedWireIndex":-1,
      "ConnectedWireSegmentIndex":-1,
      "Points":[{"x":0.0,"y":0.0},{"x":6.56464,"y":0.40414},{"x":6.56464,"y":-3.03513},{"x":0.0,"y":0.0}]
    },
    {
      "SourcePinAddress":{
        "PinID":1280870580,
        "PinOwnerID":1013134490
      },
      "TargetPinAddress":{
        "PinID":1407958138,
        "PinOwnerID":874559719
      },
      "ConnectionType":0,
      "ConnectedWireIndex":-1,
      "ConnectedWireSegmentIndex":-1,
      "Points":[{"x":0.0,"y":0.0},{"x":6.43621,"y":-0.55205},{"x":6.43621,"y":-3.28769},{"x":0.0,"y":0.0}]
    },
    {
      "SourcePinAddress":{
        "PinID":1287000259,
        "PinOwnerID":874559719
      },
      "TargetPinAddress":{
        "PinID":0,
        "PinOwnerID":1280870580
      },
      "ConnectionType":0,
      "ConnectedWireIndex":-1,
      "ConnectedWireSegmentIndex":-1,
      "Points":[{"x":0.0,"y":0.0},{"x":0.0,"y":0.0}]
    },
    {
      "SourcePinAddress":{
        "PinID":1280870580,
        "PinOwnerID":20941381
      },
      "TargetPinAddress":{
        "PinID":1407958138,
        "PinOwnerID":577456713
      },
      "ConnectionType":1,
      "ConnectedWireIndex":6,
      "ConnectedWireSegmentIndex":0,
      "Points":[{"x":6.18239,"y":0.40414},{"x":6.18239,"y":1.00044},{"x":0.0,"y":0.0}]
    },
    {
      "SourcePinAddress":{
        "PinID":39465496,
        "PinOwnerID":1013134490
      },
      "TargetPinAddress":{
        "PinID":457018231,
        "PinOwnerID":577456713
      },
      "ConnectionType":0,
      "ConnectedWireIndex":-1,
      "ConnectedWireSegmentIndex":-1,
      "Points":[{"x":0.0,"y":0.0},{"x":6.2514,"y":-0.05205},{"x":6.2514,"y":1.25647},{"x":0.0,"y":0.0}]
    },
    {
      "SourcePinAddress":{
        "PinID":1745145026,
        "PinOwnerID":1013134490
      },
      "TargetPinAddress":{
        "PinID":1407958138,
        "PinOwnerID":2041417898
      },
      "ConnectionType":0,
      "ConnectedWireIndex":-1,
      "ConnectedWireSegmentIndex":-1,
      "Points":[{"x":0.0,"y":0.0},{"x":6.40051,"y":-0.30205},{"x":6.40051,"y":0.01238},{"x":0.0,"y":0.0}]
    },
    {
      "SourcePinAddress":{
        "PinID":1280870580,
        "PinOwnerID":20941381
      },
      "TargetPinAddress":{
        "PinID":457018231,
        "PinOwnerID":2041417898
      },
      "ConnectionType":1,
      "ConnectedWireIndex":6,
      "ConnectedWireSegmentIndex":1,
      "Points":[{"x":6.56464,"y":0.26598},{"x":0.0,"y":0.0}]
    },
    {
      "SourcePinAddress":{
        "PinID":39465496,
        "PinOwnerID":20941381
      },
      "TargetPinAddress":{
        "PinID":2130172502,
        "PinOwnerID":1456596328
      },
      "ConnectionType":0,
      "ConnectedWireIndex":-1,
      "ConnectedWireSegmentIndex":-1,
      "Points":[{"x":0.0,"y":0.0},{"x":4.2287,"y":0.90414},{"x":4.2287,"y":2.01951},{"x":14.9438,"y":2.01951},{"x":14.9438,"y":1.45464},{"x":0.0,"y":0.0}]
    },
    {
      "SourcePinAddress":{
        "PinID":1745145026,
        "PinOwnerID":20941381
      },
      "TargetPinAddress":{
        "PinID":2130172502,
        "PinOwnerID":31910896
      },
      "ConnectionType":0,
      "ConnectedWireIndex":-1,
      "ConnectedWireSegmentIndex":-1,
      "Points":[{"x":0.0,"y":0.0},{"x":4.38256,"y":0.65414},{"x":4.38256,"y":1.80671},{"x":14.75492,"y":1.80671},{"x":14.75492,"y":-0.63291},{"x":0.0,"y":0.0}]
    },
    {
      "SourcePinAddress":{
        "PinID":1287000259,
        "PinOwnerID":577456713
      },
      "TargetPinAddress":{
        "PinID":1516274765,
        "PinOwnerID":1456596328
      },
      "ConnectionType":0,
      "ConnectedWireIndex":-1,
      "ConnectedWireSegmentIndex":-1,
      "Points":[{"x":0.0,"y":0.0},{"x":15.07289,"y":1.12544},{"x":15.07289,"y":1.19322},{"x":0.0,"y":0.0}]
    },
    {
      "SourcePinAddress":{
        "PinID":1287000259,
        "PinOwnerID":2041417898
      },
      "TargetPinAddress":{
        "PinID":1516274765,
        "PinOwnerID":31910896
      },
      "ConnectionType":0,
      "ConnectedWireIndex":-1,
      "ConnectedWireSegmentIndex":-1,
      "Points":[{"x":0.0,"y":0.0},{"x":14.52509,"y":0.14098},{"x":14.52509,"y":-0.85594},{"x":0.0,"y":0.0}]
    },
    {
      "SourcePinAddress":{
        "PinID":1935310050,
        "PinOwnerID":1456596328
      },
      "TargetPinAddress":{
        "PinID":0,
        "PinOwnerID":39465496
      },
      "ConnectionType":0,
      "ConnectedWireIndex":-1,
      "ConnectedWireSegmentIndex":-1,
      "Points":[{"x":0.0,"y":0.0},{"x":20.47565,"y":1.31718},{"x":20.47565,"y":0.98592},{"x":0.0,"y":0.0}]
    },
    {
      "SourcePinAddress":{
        "PinID":1935310050,
        "PinOwnerID":31910896
      },
      "TargetPinAddress":{
        "PinID":0,
        "PinOwnerID":1745145026
      },
      "ConnectionType":0,
      "ConnectedWireIndex":-1,
      "ConnectedWireSegmentIndex":-1,
      "Points":[{"x":0.0,"y":0.0},{"x":20.23117,"y":-0.74527},{"x":20.23117,"y":-1.06495},{"x":0.0,"y":0.0}]
    }
  ],
  "Displays": null,
  "FreezePinEnabled": false
}