{
  "Name": "First Tick Check",
  "NameLocation": 0,
  "ChipType": 0,
  "Size": {
    "x": 1.7,
    "y": 0.75
  },
  "Colour": {
    "r": 0.155516222,
    "g": 0.7431678,
    "b": 0.7083721,
    "a": 1
  },
  "InputPins":[
    {
      "Name":"ON",
      "ID":835858451,
      "Position":{
        "x":-6.69943,
        "y":0.98716
      },
      "BitCount":1,
      "Colour":0,
      "ValueDisplayMode":0
    },
    {
      "Name":"RESET",
      "ID":1183087480,
      "Position":{
        "x":-6.69943,
        "y":0.10634
      },
      "BitCount":1,
      "Colour":0,
      "ValueDisplayMode":0
    },
    {
      "Name":"CLOCK",
      "ID":128222680,
      "Position":{
        "x":-6.71037,
        "y":-1.09733
      },
      "BitCount":1,
      "Colour":0,
      "ValueDisplayMode":0
    }
  ],
  "OutputPins":[
    {
      "Name":"FIRST TICK",
      "ID":2116830408,
      "Position":{
        "x":3.0512,
        "y":-0.32766
      },
      "BitCount":1,
      "Colour":0,
      "ValueDisplayMode":0
    }
  ],
  "SubChips":[
    {
      "Name":"SR Latch",
      "ID":2017093723,
      "Label":"",
      "Position":{
        "x":-3.3238,
        "y":-1.81275
      },
      "OutputPinColourInfo":[{"PinColour":0,"PinID":286754339}],
      "InternalData":null
    },
    {
      "Name":"SR Latch",
      "ID":1129872057,
      "Label":"",
      "Position":{
        "x":-0.86834,
        "y":-1.2321
      },
      "OutputPinColourInfo":[{"PinColour":0,"PinID":286754339}],
      "InternalData":null
    },
    {
      "Name":"AND",
      "ID":136575764,
      "Label":"",
      "Position":{
        "x":-2.18218,
        "y":-1.69465
      },
      "OutputPinColourInfo":[{"PinColour":0,"PinID":1287000259}],
      "InternalData":null
    },
    {
      "Name":"NOT",
      "ID":940927938,
      "Label":"",
      "Position":{
        "x":-3.16141,
        "y":-1.22226
      },
      "OutputPinColourInfo":[{"PinColour":0,"PinID":49565523}],
      "InternalData":null
    },
    {
      "Name":"AND",
      "ID":997507115,
      "Label":"",
      "Position":{
        "x":-4.99685,
        "y":-1.67497
      },
      "OutputPinColourInfo":[{"PinColour":0,"PinID":1287000259}],
      "InternalData":null
    },
    {
      "Name":"NOT",
      "ID":232518480,
      "Label":"",
      "Position":{
        "x":0.32005,
        "y":-0.31456
      },
      "OutputPinColourInfo":[{"PinColour":0,"PinID":49565523}],
      "InternalData":null
    }
  ],
  "Wires":[
    {
      "SourcePinAddress":{
        "PinID":286754339,
        "PinOwnerID":2017093723
      },
      "TargetPinAddress":{
        "PinID":1407958138,
        "PinOwnerID":136575764
      },
      "ConnectionType":0,
      "ConnectedWireIndex":-1,
      "ConnectedWireSegmentIndex":-1,
      "Points":[{"x":0.0,"y":0.0},{"x":0.0,"y":0.0}]
    },
    {
      "SourcePinAddress":{
        "PinID":49565523,
        "PinOwnerID":940927938
      },
      "TargetPinAddress":{
        "PinID":457018231,
        "PinOwnerID":136575764
      },
      "ConnectionType":0,
      "ConnectedWireIndex":-1,
      "ConnectedWireSegmentIndex":-1,
      "Points":[{"x":0.0,"y":0.0},{"x":0.0,"y":0.0}]
    },
    {
      "SourcePinAddress":{
        "PinID":1287000259,
        "PinOwnerID":136575764
      },
      "TargetPinAddress":{
        "PinID":1369286925,
        "PinOwnerID":1129872057
      },
      "ConnectionType":0,
      "ConnectedWireIndex":-1,
      "ConnectedWireSegmentIndex":-1,
      "Points":[{"x":0.0,"y":0.0},{"x":0.0,"y":0.0}]
    },
    {
      "SourcePinAddress":{
        "PinID":0,
        "PinOwnerID":128222680
      },
      "TargetPinAddress":{
        "PinID":2115739022,
        "PinOwnerID":940927938
      },
      "ConnectionType":0,
      "ConnectedWireIndex":-1,
      "ConnectedWireSegmentIndex":-1,
      "Points":[{"x":0.0,"y":0.0},{"x":0.0,"y":0.0}]
    },
    {
      "SourcePinAddress":{
        "PinID":1287000259,
        "PinOwnerID":997507115
      },
      "TargetPinAddress":{
        "PinID":1369286925,
        "PinOwnerID":2017093723
      },
      "ConnectionType":0,
      "ConnectedWireIndex":-1,
      "ConnectedWireSegmentIndex":-1,
      "Points":[{"x":0.0,"y":0.0},{"x":0.0,"y":0.0}]
    },
    {
      "SourcePinAddress":{
        "PinID":0,
        "PinOwnerID":128222680
      },
      "TargetPinAddress":{
        "PinID":457018231,
        "PinOwnerID":997507115
      },
      "ConnectionType":1,
      "ConnectedWireIndex":3,
      "ConnectedWireSegmentIndex":0,
      "Points":[{"x":-5.56682,"y":-1.11698},{"x":-5.56766,"y":-1.54997},{"x":0.0,"y":0.0}]
    },
    {
      "SourcePinAddress":{
        "PinID":0,
        "PinOwnerID":835858451
      },
      "TargetPinAddress":{
        "PinID":1407958138,
        "PinOwnerID":997507115
      },
      "ConnectionType":0,
      "ConnectedWireIndex":-1,
      "ConnectedWireSegmentIndex":-1,
      "Points":[{"x":0.0,"y":0.0},{"x":-5.70544,"y":0.97731},{"x":-5.70544,"y":-1.79997},{"x":0.0,"y":0.0}]
    },
    {
      "SourcePinAddress":{
        "PinID":0,
        "PinOwnerID":1183087480
      },
      "TargetPinAddress":{
        "PinID":683460938,
        "PinOwnerID":1129872057
      },
      "ConnectionType":0,
      "ConnectedWireIndex":-1,
      "ConnectedWireSegmentIndex":-1,
      "Points":[{"x":0.0,"y":0.0},{"x":0.0,"y":0.0}]
    },
    {
      "SourcePinAddress":{
        "PinID":49565523,
        "PinOwnerID":232518480
      },
      "TargetPinAddress":{
        "PinID":0,
        "PinOwnerID":2116830408
      },
      "ConnectionType":0,
      "ConnectedWireIndex":-1,
      "ConnectedWireSegmentIndex":-1,
      "Points":[{"x":0.0,"y":0.0},{"x":0.0,"y":0.0}]
    },
    {
      "SourcePinAddress":{
        "PinID":286754339,
        "PinOwnerID":1129872057
      },
      "TargetPinAddress":{
        "PinID":2115739022,
        "PinOwnerID":232518480
      },
      "ConnectionType":0,
      "ConnectedWireIndex":-1,
      "ConnectedWireSegmentIndex":-1,
      "Points":[{"x":0.0,"y":0.0},{"x":0.0,"y":0.0}]
    },
    {
      "SourcePinAddress":{
        "PinID":0,
        "PinOwnerID":1183087480
      },
      "TargetPinAddress":{
        "PinID":683460938,
        "PinOwnerID":2017093723
      },
      "ConnectionType":1,
      "ConnectedWireIndex":7,
      "ConnectedWireSegmentIndex":0,
      "Points":[{"x":-4.03431,"y":-0.50847},{"x":0.0,"y":0.0}]
    }
  ],
  "Displays":[]
}